content_extraction/__init__.py
content_extraction/common_std_io.py
content_extraction/do_ocr.py
content_extraction/extract_from_pptx.py
content_extraction/file_handlers.py
content_extraction/fix_ocr.py
content_extraction/logging_config.py
content_extraction/parse_html.py
content_extraction/process.py
content_extraction/process_document.sh
content_extraction/semantic_chunk_html.py
content_extraction/split_and_create_digest.py
content_extraction-0.5.0.dist-info/licenses/LICENSE
content_extraction-0.5.0.dist-info/METADATA
content_extraction-0.5.0.dist-info/WHEEL
content_extraction-0.5.0.dist-info/top_level.txt
content_extraction-0.5.0.dist-info/RECORD
