Metadata-Version: 2.4
Name: content_extraction
Version: 0.5.0
Summary: Project dedicated to content extraction from unstructured files that contain some useful information.
Requires-Python: >=3.12
License-File: LICENSE
Requires-Dist: beautifulsoup4>=4.13.4
Requires-Dist: langdetect>=1.0.9
Requires-Dist: lxml>=6.0.0
Requires-Dist: python-pptx>=1.0.2
Requires-Dist: requests>=2.32.4
Dynamic: license-file
